argus/__init__.py
argus/__main__.py
argus/cli.py
argus/commands/__init__.py
argus/core/__init__.py
argus/core/base.py
argus/core/coco.py
argus/core/split.py
argus/core/yolo.py
argus_cv-1.1.0.dist-info/METADATA
argus_cv-1.1.0.dist-info/WHEEL
argus_cv-1.1.0.dist-info/entry_points.txt
argus_cv-1.1.0.dist-info/RECORD
