Metadata-Version: 2.4
Name: argus-cv
Version: 1.1.0
Summary: CLI tool for working with vision AI datasets
Requires-Python: >=3.10
Requires-Dist: numpy>=1.24.0
Requires-Dist: opencv-python>=4.8.0
Requires-Dist: pyyaml>=6.0
Requires-Dist: rich>=13.0.0
Requires-Dist: typer>=0.12.0
